cli.py
s3touch.py
s3touch-0.1.3.dist-info/DESCRIPTION.rst
s3touch-0.1.3.dist-info/METADATA
s3touch-0.1.3.dist-info/RECORD
s3touch-0.1.3.dist-info/WHEEL
s3touch-0.1.3.dist-info/entry_points.txt
s3touch-0.1.3.dist-info/metadata.json
s3touch-0.1.3.dist-info/top_level.txt
