Metadata-Version: 2.0
Name: s3touch
Version: 0.1.3
Summary: Touch files on S3.
Home-page: https://github.com/thulio/s3touch
Author: Thúlio Costa
Author-email: contact@thul.io
License: MIT
Platform: UNKNOWN
Classifier: License :: OSI Approved :: MIT License
Classifier: Topic :: Software Development :: Libraries
Classifier: Programming Language :: Python :: 2.7
Classifier: Programming Language :: Python :: 3.4
Classifier: Programming Language :: Python :: 3.5
Classifier: Programming Language :: Python :: 3.6
Classifier: Programming Language :: Python :: Implementation :: PyPy
Requires-Dist: awscli (==1.11.82)
Requires-Dist: click (==6.7)
